setup.py
PeerReviewCS485.egg-info/PKG-INFO
PeerReviewCS485.egg-info/SOURCES.txt
PeerReviewCS485.egg-info/dependency_links.txt
PeerReviewCS485.egg-info/top_level.txt
migrations/0001_initial.py
migrations/0002_auto_20141202_1314.py
migrations/0003_auto_20141202_1437.py
migrations/0004_auto_20141202_1457.py
migrations/__init__.py
test/__init__.py
test/test_integration_tests.py
test/test_system_tests.py
test/test_unit_tests.py