Metadata-Version: 1.0
Name: PeerReviewCS485
Version: 1.0
Summary: PeerReview Django app
Home-page: http://peerreview.readthedocs.org/en/latest/
Author: CS 485
Author-email: b.k.bolte@emory.edu
License: UNKNOWN
Platform: UNKNOWN
